verilog/experiment/delay_blocking_nonblocking/delay.v
`timescale 1ns/10ps

module test;

    reg a1, a2, a3, a4, b;

    // blocking
    always@(b) 
        #12 a1 = b;

    always@(b)
        a2 = #12 b;

    // nonblocking
    always@(b)
        #12 a3 <= b;

    always@(b)
        a4 <= #12 b;
/*
    initial begin

        $dumpfile("wave_lessdelay.vcd");
        $dumpvars;

        b = 0;
        #15 b = 1;
        #2 b = 0;
        #1 b = 1;
        #7 b = 0;
        #18 b = 1;
        #25 b = 0;
        #100 b = 1;
        $finish;

    end
*/

    initial begin

        $dumpfile("wave_moredelay.vcd");
        $dumpvars;

        b = 0;
        #13 b = 1;
        #13 b = 0;
        #13 b = 1;
        #13 b = 0;
        #13 b = 1;
        #13 b = 0;
        #100 b = 1;
        $finish;

    end
endmodule

verilog/experiment/delay_blocking_nonblocking/wave_moredelay.vcd
$date
	Sat Apr  1 17:41:38 2023
$end
$version
	Icarus Verilog
$end
$timescale
	10ps
$end
$scope module test $end
$var reg 1 ! a1 $end
$var reg 1 " a2 $end
$var reg 1 # a3 $end
$var reg 1 $ a4 $end
$var reg 1 % b $end
$upscope $end
$enddefinitions $end
#0
$dumpvars
0%
x$
x#
x"
x!
$end
#1200
0#
0$
0"
0!
#1300
1%
#2500
1#
1$
1!
1"
#2600
0%
#3800
0#
0$
0"
0!
#3900
1%
#5100
1#
1$
1!
1"
#5200
0%
#6400
0#
0$
0"
0!
#6500
1%
#7700
1#
1$
1!
1"
#7800
0%
#9000
0#
0$
0"
0!
#17800
1%
